[
  {
    "id": "a2d99b5b-7a09-45f1-909a-0efb542528b4",
    "userId": "user3",
    "songId": 101,
    "eventType": "like",
    "duration": 0,
    "completed": 0,
    "createdAt": "2026-04-07T16:37:10.987Z"
  },
  {
    "id": "0fafb031-91db-4a34-aeb4-04f266a0a321",
    "userId": "user_new",
    "songId": 103,
    "eventType": "skip",
    "duration": 10,
    "completed": 0,
    "createdAt": "2026-04-07T16:36:39.326Z"
  },
  {
    "id": "857a47bc-55d5-4ae8-bc4c-6fd2f64ae94d",
    "userId": "user_new",
    "songId": 102,
    "eventType": "like",
    "duration": 0,
    "completed": 0,
    "createdAt": "2026-04-07T16:36:39.315Z"
  },
  {
    "id": "bda7c157-c5bf-4235-8e06-2e303398ae2d",
    "userId": "user_new",
    "songId": 102,
    "eventType": "play",
    "duration": 270,
    "completed": 1,
    "createdAt": "2026-04-07T16:36:39.304Z"
  },
  {
    "id": "5c3414dd-feda-4ddb-b426-7ab0ad2bd4d7",
    "userId": "user_new",
    "songId": 101,
    "eventType": "like",
    "duration": 0,
    "completed": 0,
    "createdAt": "2026-04-07T16:36:39.294Z"
  },
  {
    "id": "7602844c-725d-4fd0-a28e-4aaef5ffca04",
    "userId": "user_new",
    "songId": 101,
    "eventType": "play",
    "duration": 240,
    "completed": 1,
    "createdAt": "2026-04-07T16:36:39.283Z"
  },
  {
    "id": "e50c55d8-d4b3-46ac-bf9e-f240e5f81f1d",
    "userId": "user1",
    "songId": 4,
    "eventType": "skip",
    "duration": 10,
    "completed": 0,
    "createdAt": "2026-04-07T16:27:46.257Z"
  },
  {
    "id": "76010390-af1f-4ca1-abc5-877668c6c089",
    "userId": "user1",
    "songId": 3,
    "eventType": "play",
    "duration": 225,
    "completed": 1,
    "createdAt": "2026-04-07T16:27:46.245Z"
  },
  {
    "id": "f3ca3bdc-16d5-4bbb-a1c1-db4fbc80d09b",
    "userId": "user1",
    "songId": 2,
    "eventType": "like",
    "duration": 0,
    "completed": 0,
    "createdAt": "2026-04-07T16:27:46.236Z"
  },
  {
    "id": "bc7e39b0-2b92-4392-b0f6-c222832167d0",
    "userId": "user1",
    "songId": 2,
    "eventType": "play",
    "duration": 270,
    "completed": 1,
    "createdAt": "2026-04-07T16:27:46.226Z"
  },
  {
    "id": "b429fad8-8a73-451e-bf6e-8287d6cab192",
    "userId": "user1",
    "songId": 1,
    "eventType": "like",
    "duration": 0,
    "completed": 0,
    "createdAt": "2026-04-07T16:27:46.216Z"
  },
  {
    "id": "059580db-bceb-4a39-9472-48e433058cf4",
    "userId": "user1",
    "songId": 1,
    "eventType": "play",
    "duration": 240,
    "completed": 1,
    "createdAt": "2026-04-07T16:27:46.204Z"
  }
]